{
    "@context": [
        "https://doi.org/10.5063/schema/codemeta-2.0",
        "http://schema.org"
    ],
    "@type": "SoftwareSourceCode",
    "identifier": "https://doi.org/10.5281/zenodo.17980054",
    "name": "sofia-redux",
    "description": "SOFIA data reduction pipelines",
    "license": "BSD 3-Clause",
    "author": [
        {
            "@type": "Organization",
            "givenName": "SOFIA-USRA",
            "email": "mclarke@sofia.usra.edu"
        },
        {
            "@type": "Organization",
            "givenName": "SOFIA Data Center",
            "email": "sdc-redux@irs.uni-stuttgart.de"
        }        
    ],
    "provider": {
        "@id": "https://pypi.org",
        "@type": "Organization",
        "name": "The Python Package Index",
        "url": "https://pypi.org"
    },
    "runtimePlatform": "Python 3",
    "url": "https://github.com/SOFIA-Data-Center/sofia_redux"
}
