{
    "id": "TOPOLIB-1",
    "name": "Abilene",
    "short_name": "US-11",
    "nodes": [
        {
            "id": 0,
            "name": "Seattle",
            "longitude": -122.3328481,
            "latitude": 47.6061389,
            "pop": 780995,
            "DC": 58,
            "IXP": 5
        },
        {
            "id": 1,
            "name": "Sunnyvale",
            "longitude": -122.0363496,
            "latitude": 37.36883,
            "pop": 155805,
            "DC": 0,
            "IXP": 0
        },
        {
            "id": 2,
            "name": "Los Angeles",
            "longitude": -118.242643,
            "latitude": 34.0549076,
            "pop": 3820914,
            "DC": 71,
            "IXP": 9
        },
        {
            "id": 3,
            "name": "Denver",
            "longitude": -104.990251,
            "latitude": 39.7392358,
            "pop": 729019,
            "DC": 49,
            "IXP": 6
        },
        {
            "id": 4,
            "name": "Kansas City",
            "longitude": -94.5785667,
            "latitude": 39.0997265,
            "pop": 475378,
            "DC": 25,
            "IXP": 1
        },
        {
            "id": 5,
            "name": "Houston",
            "longitude": -95.3701108,
            "latitude": 29.7600771,
            "pop": 2314157,
            "DC": 55,
            "IXP": 6
        },
        {
            "id": 6,
            "name": "Atlanta",
            "longitude": -84.3885209,
            "latitude": 33.7501275,
            "pop": 510823,
            "DC": 145,
            "IXP": 7
        },
        {
            "id": 7,
            "name": "Indianapolis",
            "longitude": -86.158018,
            "latitude": 39.76909,
            "pop": 887642,
            "DC": 30,
            "IXP": 2
        },
        {
            "id": 8,
            "name": "Chicago",
            "longitude": -87.6323879,
            "latitude": 41.88325,
            "pop": 2664452,
            "DC": 165,
            "IXP": 10
        },
        {
            "id": 9,
            "name": "Washington D.C.",
            "longitude": -77.0368707,
            "latitude": 38.9071923,
            "pop": 689545,
            "DC": 7,
            "IXP": 3
        },
        {
            "id": 10,
            "name": "New York",
            "longitude": -74.0059728,
            "latitude": 40.7127753,
            "pop": 8804190,
            "DC": 70,
            "IXP": 11
        }
    ],
    "links": [
        {
            "id": 0,
            "src": 0,
            "dst": 1,
            "length": 1482.26
        },
        {
            "id": 1,
            "src": 2,
            "dst": 1,
            "length": 649.31
        },
        {
            "id": 2,
            "src": 5,
            "dst": 2,
            "length": 2870.2
        },
        {
            "id": 3,
            "src": 4,
            "dst": 5,
            "length": 1360.7
        },
        {
            "id": 4,
            "src": 3,
            "dst": 0,
            "length": 2123.16
        },
        {
            "id": 5,
            "src": 3,
            "dst": 1,
            "length": 1949.85
        },
        {
            "id": 6,
            "src": 4,
            "dst": 3,
            "length": 1153.26
        },
        {
            "id": 7,
            "src": 8,
            "dst": 7,
            "length": 345.36
        },
        {
            "id": 8,
            "src": 4,
            "dst": 7,
            "length": 933.65
        },
        {
            "id": 9,
            "src": 5,
            "dst": 6,
            "length": 1471.24
        },
        {
            "id": 10,
            "src": 6,
            "dst": 7,
            "length": 912.61
        },
        {
            "id": 11,
            "src": 10,
            "dst": 8,
            "length": 1489.76
        },
        {
            "id": 12,
            "src": 6,
            "dst": 9,
            "length": 1126.74
        },
        {
            "id": 13,
            "src": 9,
            "dst": 10,
            "length": 416.12
        },
        {
            "id": 14,
            "src": 1,
            "dst": 0,
            "length": 1482.26
        },
        {
            "id": 15,
            "src": 1,
            "dst": 2,
            "length": 649.31
        },
        {
            "id": 16,
            "src": 2,
            "dst": 5,
            "length": 2870.2
        },
        {
            "id": 17,
            "src": 5,
            "dst": 4,
            "length": 1360.7
        },
        {
            "id": 18,
            "src": 0,
            "dst": 3,
            "length": 2123.16
        },
        {
            "id": 19,
            "src": 1,
            "dst": 3,
            "length": 1949.85
        },
        {
            "id": 20,
            "src": 3,
            "dst": 4,
            "length": 1153.26
        },
        {
            "id": 21,
            "src": 7,
            "dst": 8,
            "length": 345.36
        },
        {
            "id": 22,
            "src": 7,
            "dst": 4,
            "length": 933.65
        },
        {
            "id": 23,
            "src": 6,
            "dst": 5,
            "length": 1471.24
        },
        {
            "id": 24,
            "src": 7,
            "dst": 6,
            "length": 912.61
        },
        {
            "id": 25,
            "src": 8,
            "dst": 10,
            "length": 1489.76
        },
        {
            "id": 26,
            "src": 9,
            "dst": 6,
            "length": 1126.74
        },
        {
            "id": 27,
            "src": 10,
            "dst": 9,
            "length": 416.12
        }
    ],
    "Source": {
        "url": "https://ieeexplore.ieee.org/document/4389246",
        "paper": "Malware Filtering for Network Security Using Weighted Optimality Measures",
        "doi": "10.1109/CCA.2007.4389246"
    },
    "capacity": {
        "pop": 0.015,
        "DC": 400,
        "IXP": 2857
    }
}