{
  "name": "ragas_ko90_en10_sample",
  "version": "1.0.0",
  "thresholds": {
    "faithfulness": 0.7,
    "answer_relevancy": 0.7,
    "context_precision": 0.6,
    "context_recall": 0.6
  },
  "test_cases": [
    {
      "id": "tc-001",
      "question": "서울의 수도는 어디인가요?",
      "answer": "대한민국의 수도는 서울입니다.",
      "contexts": ["대한민국의 수도는 서울이며 정치, 경제, 문화의 중심지입니다."],
      "ground_truth": "대한민국의 수도는 서울입니다."
    },
    {
      "id": "tc-002",
      "question": "지구는 태양을 한 바퀴 도는 데 얼마나 걸리나요?",
      "answer": "지구는 태양을 한 바퀴 도는 데 약 1년이 걸립니다.",
      "contexts": ["지구의 공전 주기는 약 365일이며 이를 1년이라고 부릅니다."],
      "ground_truth": "지구의 공전 주기는 약 365일입니다."
    },
    {
      "id": "tc-003",
      "question": "한글을 만든 사람은 누구인가요?",
      "answer": "한글은 세종대왕이 만들었습니다.",
      "contexts": ["훈민정음은 세종대왕이 창제하여 1446년에 반포되었습니다."],
      "ground_truth": "한글은 세종대왕이 창제했습니다."
    },
    {
      "id": "tc-004",
      "question": "물의 화학식은 무엇인가요?",
      "answer": "물의 화학식은 H2O입니다.",
      "contexts": ["물 분자는 수소 2개와 산소 1개로 구성되어 H2O로 표시됩니다."],
      "ground_truth": "물의 화학식은 H2O입니다."
    },
    {
      "id": "tc-005",
      "question": "대한민국의 국화는 무엇인가요?",
      "answer": "대한민국의 국화는 무궁화입니다.",
      "contexts": ["무궁화는 대한민국을 상징하는 꽃으로 국화로 지정되어 있습니다."],
      "ground_truth": "대한민국의 국화는 무궁화입니다."
    },
    {
      "id": "tc-006",
      "question": "삼각형의 내각의 합은 몇 도인가요?",
      "answer": "삼각형의 내각의 합은 180도입니다.",
      "contexts": ["유클리드 기하학에서 삼각형의 내각의 합은 180도입니다."],
      "ground_truth": "삼각형의 내각의 합은 180도입니다."
    },
    {
      "id": "tc-007",
      "question": "대한민국의 화폐 단위는 무엇인가요?",
      "answer": "대한민국의 화폐 단위는 원입니다.",
      "contexts": ["대한민국의 공식 화폐 단위는 원(KRW)입니다."],
      "ground_truth": "대한민국의 화폐 단위는 원입니다."
    },
    {
      "id": "tc-008",
      "question": "빛의 속도는 진공에서 약 얼마인가요?",
      "answer": "빛의 속도는 진공에서 약 299,792km/s입니다.",
      "contexts": ["빛의 속도는 진공에서 약 299,792킬로미터 매초입니다."],
      "ground_truth": "빛의 속도는 진공에서 약 299,792km/s입니다."
    },
    {
      "id": "tc-009",
      "question": "인공지능은 무엇을 의미하나요?",
      "answer": "인공지능은 인간의 지능을 모방해 학습·추론·문제 해결을 수행하는 기술을 의미합니다.",
      "contexts": ["인공지능(AI)은 데이터로부터 학습하고 추론하여 문제를 해결하는 컴퓨터 기술입니다."],
      "ground_truth": "인공지능은 학습과 추론을 통해 문제를 해결하는 기술입니다."
    },
    {
      "id": "tc-010",
      "question": "What is the capital of France?",
      "answer": "The capital of France is Paris.",
      "contexts": ["Paris is the capital and most populous city of France."],
      "ground_truth": "Paris is the capital of France."
    }
  ]
}
